{"data":[{"type":"activity","name":"BBQing","id":"ac3","created_at":1372374427,"total_editorial_playlists":77},{"type":"activity","name":"Being Blue","id":"ac38","created_at":1388798265,"total_editorial_playlists":72},{"type":"activity","name":"Breaking Up","id":"ac44","created_at":1389053378,"total_editorial_playlists":60},{"type":"activity","name":"Celebrating","id":"ac7","created_at":1375878881,"total_editorial_playlists":79},{"type":"activity","name":"Chilling Out","id":"ac1","created_at":1372374396,"total_editorial_playlists":100},{"type":"activity","name":"Cooking","id":"ac27","created_at":1377894259,"total_editorial_playlists":46},{"type":"activity","name":"Dancing","id":"ac9","created_at":1375878949,"total_editorial_playlists":100},{"type":"activity","name":"Dreaming","id":"ac11","created_at":1375878973,"total_editorial_playlists":62},{"type":"activity","name":"Drinking","id":"ac12","created_at":1375878979,"total_editorial_playlists":59},{"type":"activity","name":"Driving","id":"ac5","created_at":1372374427,"total_editorial_playlists":100},{"type":"activity","name":"Entertaining","id":"ac24","created_at":1375879054,"total_editorial_playlists":57},{"type":"activity","name":"Getting It On","id":"ac39","created_at":1388798979,"total_editorial_playlists":44},{"type":"activity","name":"Getting Pumped","id":"ac41","created_at":1388801813,"total_editorial_playlists":51},{"type":"activity","name":"Getting Ready to Go Out","id":"ac35","created_at":1385410287,"total_editorial_playlists":54},{"type":"activity","name":"Kicking Back","id":"ac40","created_at":1388799881,"total_editorial_playlists":96},{"type":"activity","name":"Partying","id":"ac20","created_at":1375879035,"total_editorial_playlists":100},{"type":"activity","name":"Partying Poolside","id":"ac43","created_at":1388804046,"total_editorial_playlists":57},{"type":"activity","name":"Pre-Partying","id":"ac21","created_at":1375879040,"total_editorial_playlists":66},{"type":"activity","name":"Punching Walls","id":"ac28","created_at":1377894292,"total_editorial_playlists":50},{"type":"activity","name":"Romancing","id":"ac2","created_at":1372374422,"total_editorial_playlists":100}],"info":{"offset":0,"count":20,"total":27},"code":"OK"}
